<annotation>
	<folder>JPEGImages</folder>
	<filename>93.png</filename>
	<path>E:\cache\Desktop\YOLO\VOCdevkit\VOC2007-Hero\JPEGImages\93.png</path>
	<source>
		<database>Unknown</database>
	</source>
	<size>
		<width>1920</width>
		<height>1032</height>
		<depth>3</depth>
	</size>
	<segmented>0</segmented>
	<object>
		<name>Hero</name>
		<pose>Unspecified</pose>
		<truncated>0</truncated>
		<difficult>0</difficult>
		<bndbox>
			<xmin>903</xmin>
			<ymin>412</ymin>
			<xmax>1029</xmax>
			<ymax>586</ymax>
		</bndbox>
	</object>
	<object>
		<name>Lizard</name>
		<pose>Unspecified</pose>
		<truncated>0</truncated>
		<difficult>0</difficult>
		<bndbox>
			<xmin>9</xmin>
			<ymin>344</ymin>
			<xmax>194</xmax>
			<ymax>423</ymax>
		</bndbox>
	</object>
	<object>
		<name>Lizard</name>
		<pose>Unspecified</pose>
		<truncated>0</truncated>
		<difficult>0</difficult>
		<bndbox>
			<xmin>12</xmin>
			<ymin>270</ymin>
			<xmax>119</xmax>
			<ymax>340</ymax>
		</bndbox>
	</object>
	<object>
		<name>Buff</name>
		<pose>Unspecified</pose>
		<truncated>0</truncated>
		<difficult>0</difficult>
		<bndbox>
			<xmin>682</xmin>
			<ymin>346</ymin>
			<xmax>995</xmax>
			<ymax>625</ymax>
		</bndbox>
	</object>
</annotation>
